har2warc/__init__.py
har2warc/har2warc.py
har2warc-1.0.4.data/data/test/data/example.har
har2warc-1.0.4.data/data/test/data/http2.github.io.har
har2warc-1.0.4.dist-info/DESCRIPTION.rst
har2warc-1.0.4.dist-info/METADATA
har2warc-1.0.4.dist-info/RECORD
har2warc-1.0.4.dist-info/WHEEL
har2warc-1.0.4.dist-info/entry_points.txt
har2warc-1.0.4.dist-info/metadata.json
har2warc-1.0.4.dist-info/top_level.txt
har2warc-1.0.4.dist-info/zip-safe
