Metadata-Version: 2.0
Name: har2warc
Version: 1.0.4
Summary: Convert HTTP Archive (HAR) -> Web Archive (WARC) format
Home-page: https://github.com/webrecorder/har2warc
Author: Ilya Kreymer
Author-email: ikreymer@gmail.com
License: Apache 2.0
Platform: UNKNOWN
Classifier: Development Status :: 4 - Beta
Classifier: Environment :: Web Environment
Classifier: License :: OSI Approved :: Apache Software License
Classifier: Programming Language :: Python :: 2
Classifier: Programming Language :: Python :: 2.7
Classifier: Programming Language :: Python :: 3
Classifier: Programming Language :: Python :: 3.3
Classifier: Programming Language :: Python :: 3.4
Classifier: Programming Language :: Python :: 3.5
Classifier: Programming Language :: Python :: 3.6
Classifier: Topic :: Software Development :: Libraries :: Python Modules
Classifier: Topic :: Utilities
Provides: har2warc
Requires-Dist: warcio
Requires-Dist: six
Requires-Dist: http-status
